{
  "updatedAt": "2026-04-25T06:05:44.576Z",
  "items": [
    {
      "title": "Jessie&#8217;s Boots Become A Toy Story x Crocs Collaboration",
      "link": "https://sneakernews.com/2026/04/24/toy-story-crocs-release-date-2026/",
      "date": "Fri, 24 Apr 2026 22:00:49 +0000",
      "source": "https://sneakernews.com/feed/"
    },
    {
      "title": "Miaou&#8217;s Zippered adidas Megaride S2 Ushers In 2000s Football Edge",
      "link": "https://sneakernews.com/2026/04/24/miaou-adidas-megaride-s2-release-date/",
      "date": "Fri, 24 Apr 2026 21:30:14 +0000",
      "source": "https://sneakernews.com/feed/"
    },
    {
      "title": "The adidas Samba Becomes A Bowling Shoe In Two Glossy Colorways",
      "link": "https://sneakernews.com/2026/04/24/adidas-samba-bowling-shoes-ki9995-kk2824/",
      "date": "Fri, 24 Apr 2026 21:00:24 +0000",
      "source": "https://sneakernews.com/feed/"
    },
    {
      "title": "Fernando Mendoza, The NFL&#8217;s Top Pick Of The Draft, Receives Custom adidas Stan Smith by The Surgeon",
      "link": "https://sneakernews.com/2026/04/24/adidas-stan-smith-the-surgeon-fernando-mendoza/",
      "date": "Fri, 24 Apr 2026 20:30:53 +0000",
      "source": "https://sneakernews.com/feed/"
    },
    {
      "title": "Nike Transforms The Sabrina 3 Into A Baseball Cleat For The Oregon Ducks And The Grateful Dead",
      "link": "https://sneakernews.com/2026/04/24/nike-sabrina-3-grateful-dead-oregon-ducks-baseball-cleat-pe/",
      "date": "Fri, 24 Apr 2026 19:57:57 +0000",
      "source": "https://sneakernews.com/feed/"
    },
    {
      "title": "Hippopotamus and NEIGHBORHOOD Drop Leopard-Print Toweling Collaboration",
      "link": "https://hypebeast.com/2026/4/hippopotamus-neighborhood-leopard-collaboration-collection-release-info",
      "date": "Wed, 22 Apr 2026 09:01:17 +0000",
      "source": "https://hypebeast.com/feed"
    }
  ]
}